{
"1733": {"descrizione":"Gattuso e Bianchi a Gallarate. Ittica, gastronomia e bistrot. Nato dall'amicizia tra pasticcere Andrea Bianchi e Rino Gattuso.","note":"Ristorante/itica. Consumi per refrigerazione e cucina.","punteggio":3},
"1734": {"descrizione":"Dorsoduro - cicchetteria veneziana a Gallarate.","note":"Enoteca con cucina. Consumi medi.","punteggio":2},
"1738": {"descrizione":"Boa Vida Churrascaria a Gallarate. Grigliate brasiliane.","note":"Ristorante. Consumi per griglia.","punteggio":3},
"1739": {"descrizione":"Cuore e Midollo - ristorante fine dining.","note":"Ristorante. Consumi medi.","punteggio":2},
"1740": {"descrizione":"Norcinarte a Gallarate. Cucina italiana.","note":"Ristorante. Consumi medi.","punteggio":2},
"1741": {"descrizione":"Mangia e Pasta a Gallarate.","note":"Ristorante. Consumi medi.","punteggio":2},
"1742": {"descrizione":"Ristorante Albatros a Gallarate. Importatore diretto di caviale.","note":"Ristorante di alto livello. Consumi medi.","punteggio":3},
"1743": {"descrizione":"Osteria Dul Tarlisu a Busto Arsizio. Fine dining con radici lombarde, carni selezionate.","note":"Ristorante fine dining. Consumi medi.","punteggio":3},
"1744": {"descrizione":"Osteria Bistrot a Busto Arsizio.","note":"Osteria. Consumi medi.","punteggio":2},
"1745": {"descrizione":"Tavolo Unico a Busto Arsizio. Ristorante.","note":"Ristorante. Consumi medi.","punteggio":2},
"1746": {"descrizione":"Chef DEG Ristorante Cucina Democratica a Busto Arsizio. Cucina contemporanea.","note":"Ristorante contemporaneo. Consumi medi.","punteggio":2},
"1748": {"descrizione":"Ristorante Gustoo a Busto Arsizio. Cucina italiana con materie prime di qualità.","note":"Ristorante. Consumi medi.","punteggio":2},
"1750": {"descrizione":"Il Mannarino Busto Arsizio. Macelleria con cucina. Scegli la carne al banco e gustala a tavola.","note":"Macelleria + ristorante. Consumi per refrigerazione e cottura.","punteggio":3},
"1751": {"descrizione":"Ristorante El Parrillero a Busto Arsizio.","note":"Ristorante. Consumi medi.","punteggio":2},
"1753": {"descrizione":"Trattoria del Municipio a Busto Arsizio. Cucina italiana, anche senza glutine.","note":"Trattoria. Consumi medi.","punteggio":2},
"1756": {"descrizione":"Diverso Ristorante Contemporaneo a Busto Arsizio. Chef Marco, tagli rari e frollature.","note":"Ristorante. Consumi medi.","punteggio":2},
"1757": {"descrizione":"Trattoria Caprese a Busto Arsizio.","note":"Trattoria. Consumi medi.","punteggio":2},
"1758": {"descrizione":"Ristorante Mirò a Busto Arsizio. In cortile del '700.","note":"Ristorante storico. Consumi medi.","punteggio":3},
"1759": {"descrizione":"Grani in Bottega a Busto Arsizio. Pizzeria di tradizione romana e bottega.","note":"Pizzeria. Consumi forno.","punteggio":2},
"1760": {"descrizione":"Karma Ristorante Pizzeria a Busto Arsizio. Pizza napoletana contemporanea.","note":"Pizzeria. Consumi forno.","punteggio":2},
"1761": {"descrizione":"Kuwagata - ristorante giapponese autentico a Busto Arsizio.","note":"Ristorante giapponese. Consumi medi.","punteggio":2},
"1764": {"descrizione":"Il Passerotto a Saronno. Osteria con cucina dal 1890. Cucina milanese, materie prime locali.","note":"Osteria storica. Consumi medi.","punteggio":3},
"1765": {"descrizione":"Il Mannarino Saronno. Macelleria con cucina.","note":"Macelleria + ristorante. Consumi refrigerazione.","punteggio":3},
"1767": {"descrizione":"I Poeti del Gusto a Saronno. Cantina e cucina d'autore.","note":"Ristorante. Consumi medi.","punteggio":2},
"1768": {"descrizione":"Scibui - osteria moderna a Saronno. Ispirazione giapponese Shibui. Dal 2005.","note":"Ristorante. Consumi medi.","punteggio":2},
"1769": {"descrizione":"Quanto Basta - caffè & cucina a Saronno dal 1953. Bistrot.","note":"Bar/bistrot. Consumi medi.","punteggio":2},
"1770": {"descrizione":"Hashtag15 - ristorante e bistrot a Saronno. Incontro tra tradizione e creatività.","note":"Bistrot. Consumi medi.","punteggio":2},
"1771": {"descrizione":"La Vecchia Fiorentina a Saronno. 45 anni di esperienza della famiglia Galli.","note":"Ristorante. Consumi medi.","punteggio":2},
"1775": {"descrizione":"Olio fishbar a Saronno. Cucina di pesce.","note":"Ristorante pesce. Consumi medi.","punteggio":2},
"1776": {"descrizione":"Da Biagio Ristorante Positano a Saronno. Specialità di pesce e tradizioni campane.","note":"Ristorante di pesce. Consumi medi.","punteggio":2},
"1778": {"descrizione":"Murataya - trattoria giapponese a Saronno. Chef Hitoshi Murata. Cucina tradizionale giapponese.","note":"Ristorante giapponese. Consumi medi.","punteggio":2},
"1779": {"descrizione":"Ristorante Boeucc a Saronno.","note":"Ristorante. Consumi medi.","punteggio":2},
"1782": {"descrizione":"Well Sushi a Saronno, Solbiate Arno e Bovisio Masciago. Asian fusion all you can eat.","note":"Ristorante sushi. Consumi medi.","punteggio":2},
"1783": {"descrizione":"Ristorante L'Armonica a Tradate. Specialità mediterranee rivisitate.","note":"Ristorante. Consumi medi.","punteggio":2},
"1784": {"descrizione":"La Cucina del Quarantadue a Tradate.","note":"Ristorante. Consumi medi.","punteggio":2},
"1785": {"descrizione":"Ristorante Tradate 1921. Fine dining.","note":"Ristorante. Consumi medi.","punteggio":2},
"1787": {"descrizione":"Oro Rosso a Tradate. Ristorante pizzeria nel centro.","note":"Ristorante pizzeria. Consumi forno.","punteggio":2},
"1788": {"descrizione":"Ciboom a Tradate. Pizza contemporanea.","note":"Pizzeria. Consumi forno.","punteggio":2},
"1789": {"descrizione":"Ristorante Da Vincenzo a Tradate (ex Da Vinci Srl). Dal 1969, famiglia Vuolo.","note":"Ristorante storico. Consumi medi.","punteggio":3},
"1790": {"descrizione":"Birra & Brace - griglieria pinseria. Catena con sedi a Lecco, Bergamo, Monza, Solaro.","note":"Catena ristoranti. Consumi medio-alti.","punteggio":3},
"1791": {"descrizione":"Spazio Libero a Tradate. Pizzeria con specialità carne e paella.","note":"Ristorante/pizzeria. Consumi forno.","punteggio":2},
"1792": {"descrizione":"Agriturismo Il Castagno a Tradate nel Parco Pineta.","note":"Agriturismo. Consumi medi.","punteggio":3},
"1794": {"descrizione":"La Gastronomia di Tradate. Catering per aziende e privati.","note":"Gastronomia/catering. Consumi medi.","punteggio":2},
"1795": {"descrizione":"Old Wild West Tradate - steakhouse catena.","note":"Ristorante catena. Consumi medi.","punteggio":2},
"1796": {"descrizione":"K Kaiseki Sushi Garden a Tradate.","note":"Sushi. Consumi medi.","punteggio":2},
"1799": {"descrizione":"Pizzikotto Tradate - pizzeria e lifferia.","note":"Pizzeria. Consumi forno.","punteggio":2},
"1800": {"descrizione":"In & Out Pizzeria e Pasticceria a Tradate. Colazioni, pranzi, aperitivi.","note":"Pizzeria/pasticceria. Consumi forno.","punteggio":2},
"1802": {"descrizione":"Osteria degli Angeli a Malnate.","note":"Osteria. Consumi medi.","punteggio":2},
"1803": {"descrizione":"Crotto Valtellina a Malnate. Chef Roberto Valbuzzi. Specialità valtellinesi.","note":"Ristorante. Consumi medi.","punteggio":3},
"1804": {"descrizione":"Diodona Spazio & Ristorante a Malnate. Location per matrimoni e ristorante raffinato. 5 ettari.","note":"Location eventi + ristorante. Consumi medio-alti.","punteggio":3}
}
